hdxms_datasets/__init__.py
hdxms_datasets/__main__.py
hdxms_datasets/__version__.py
hdxms_datasets/_version.py
hdxms_datasets/convert.py
hdxms_datasets/database.py
hdxms_datasets/expr.py
hdxms_datasets/formats.py
hdxms_datasets/loader.py
hdxms_datasets/models.py
hdxms_datasets/plot.py
hdxms_datasets/process.py
hdxms_datasets/utils.py
hdxms_datasets/verification.py
hdxms_datasets/view.py
hdxms_datasets/migration/v020.py
hdxms_datasets/stable/v020/backend.py
hdxms_datasets/stable/v020/convert.py
hdxms_datasets/stable/v020/datasets.py
hdxms_datasets/stable/v020/datavault.py
hdxms_datasets/stable/v020/expr.py
hdxms_datasets/stable/v020/formats.py
hdxms_datasets/stable/v020/plot.py
hdxms_datasets/stable/v020/process.py
hdxms_datasets/stable/v020/reader.py
hdxms_datasets/stable/v020/utils.py
hdxms_datasets/template/CITATION.cff
hdxms_datasets/template/hdx_spec.yaml
hdxms_datasets/template/metadata.yaml
hdxms_datasets/template/data/data_file.csv
hdxms_datasets/web/components.py
hdxms_datasets/web/models.py
hdxms_datasets/web/state.py
hdxms_datasets/web/upload_form.py
hdxms_datasets-0.3.1.dist-info/METADATA
hdxms_datasets-0.3.1.dist-info/WHEEL
hdxms_datasets-0.3.1.dist-info/entry_points.txt
hdxms_datasets-0.3.1.dist-info/licenses/AUTHORS.rst
hdxms_datasets-0.3.1.dist-info/licenses/LICENSE
hdxms_datasets-0.3.1.dist-info/RECORD
