Metadata-Version: 2.4
Name: hdxms-datasets
Version: 0.3.1
Summary: Download and parse curated HDX-MS datasets
Project-URL: Source, https://github.com/Jhsmit/hdxms-datasets/
Project-URL: Documentation, https://jhsmit.github.io/hdxms-datasets/
Author-email: Jochem Smit <jhsmit@gmail.com>
License-Expression: MIT
License-File: AUTHORS.rst
License-File: LICENSE
Classifier: Development Status :: 2 - Pre-Alpha
Classifier: Intended Audience :: Science/Research
Classifier: Programming Language :: Python :: 3.11
Classifier: Programming Language :: Python :: 3.12
Classifier: Programming Language :: Python :: 3.13
Classifier: Programming Language :: Python :: 3.14
Requires-Python: >=3.11
Requires-Dist: narwhals>=2.7.0
Requires-Dist: numpy
Requires-Dist: pydantic
Requires-Dist: pyyaml
Requires-Dist: requests
Requires-Dist: statsmodels
Requires-Dist: typer>=0.9.0
Requires-Dist: uncertainties
Provides-Extra: dev
Requires-Dist: black[jupyter]>=22.12.0; extra == 'dev'
Provides-Extra: docs
Requires-Dist: jupyter>=1.0.0; extra == 'docs'
Requires-Dist: mkdocs-gen-files>=0.4.0; extra == 'docs'
Requires-Dist: mkdocs-jupyter>=0.22.0; extra == 'docs'
Requires-Dist: mkdocs-literate-nav>=0.5.0; extra == 'docs'
Requires-Dist: mkdocs-material>=8.5.11; extra == 'docs'
Requires-Dist: mkdocs>=1.4.2; extra == 'docs'
Requires-Dist: mkdocstrings[python]>=0.19.1; extra == 'docs'
Requires-Dist: pygments>=2.13.0; extra == 'docs'
Provides-Extra: plot
Requires-Dist: altair; extra == 'plot'
Requires-Dist: cmap; extra == 'plot'
Requires-Dist: numpy; extra == 'plot'
Requires-Dist: polars; extra == 'plot'
Provides-Extra: test
Requires-Dist: biopython; extra == 'test'
Requires-Dist: polars; extra == 'test'
Requires-Dist: pytest>=7.2.0; extra == 'test'
Provides-Extra: web
Requires-Dist: solara; extra == 'web'
